spacetimepy/__init__.py
spacetimepy/__main__.py
spacetimepy/app.py
spacetimepy/graphics/__init__.py
spacetimepy/graphics/dataPlot.py
spacetimepy/graphics/dataSort.py
spacetimepy/input/__init__.py
spacetimepy/input/readData.py
spacetimepy/input/spacetimetest.py
spacetimepy/objects/__init__.py
spacetimepy/objects/cubeMeta.py
spacetimepy/objects/cubeObject.py
spacetimepy/objects/fileObject.py
spacetimepy/objects/interumCube.py
spacetimepy/objects/writeNETCDF.py
spacetimepy/operations/__init__.py
spacetimepy/operations/cubeSmasher.py
spacetimepy/operations/cubeToDataframe.py
spacetimepy/operations/loadCube.py
spacetimepy/operations/makeCube.py
spacetimepy/operations/time.py
spacetimepy/output/__init__.py
spacetimepy/output/writeCSV.py
spacetimepy/output/writeCube.py
spacetimepy/output/writeFile.py
spacetimepy/scale/__init__.py
spacetimepy/scale/mergeData.py
spacetimepy/scale/rasterAlign.py
spacetimepy/scale/rasterTrim.py
spacetimepy-0.1.6.dist-info/LICENSE.txt
spacetimepy-0.1.6.dist-info/METADATA
spacetimepy-0.1.6.dist-info/WHEEL
spacetimepy-0.1.6.dist-info/top_level.txt
spacetimepy-0.1.6.dist-info/RECORD
