Metadata-Version: 2.1
Name: spacetimepy
Version: 0.1.6
Summary: A toolkit for working with spatiotemporal data
Author: P. A. Burnham et al.
Author-email: alexburn17@gmail.com
License: GNU GPLv3
Platform: UNKNOWN
License-File: LICENSE.txt
Requires-Dist: pandas
Requires-Dist: numpy
Requires-Dist: gdal
Requires-Dist: xarray
Requires-Dist: psutil
Requires-Dist: plotly-express
Requires-Dist: netCDF4
